sdialog/__init__.py
sdialog/agents.py
sdialog/base.py
sdialog/datasets.py
sdialog/personas.py
sdialog/server.py
sdialog/util.py
sdialog/audio/__init__.py
sdialog/audio/acoustics_simulator.py
sdialog/audio/dialog.py
sdialog/audio/dscaper_utils.py
sdialog/audio/impulse_response_database.py
sdialog/audio/jsalt.py
sdialog/audio/pipeline.py
sdialog/audio/processing.py
sdialog/audio/room.py
sdialog/audio/room_generator.py
sdialog/audio/turn.py
sdialog/audio/utils.py
sdialog/audio/voice_database.py
sdialog/audio/tts/__init__.py
sdialog/audio/tts/base.py
sdialog/audio/tts/huggingface/__init__.py
sdialog/audio/tts/huggingface/tts.py
sdialog/audio/tts/index/__init__.py
sdialog/audio/tts/index/tts.py
sdialog/audio/tts/kokoro/__init__.py
sdialog/audio/tts/kokoro/tts.py
sdialog/config/__init__.py
sdialog/config/config.yaml
sdialog/evaluation/__init__.py
sdialog/evaluation/base.py
sdialog/evaluation/dialog2flow/__init__.py
sdialog/evaluation/dialog2flow/build_graph.py
sdialog/evaluation/dialog2flow/extract_trajectories.py
sdialog/evaluation/dialog2flow/util/__init__.py
sdialog/evaluation/dialog2flow/util/visualization/graph.html
sdialog/evaluation/dialog2flow/util/visualization/imgs/plus-icon-13066.png
sdialog/evaluation/dialog2flow/util/visualization/imgs/plus_4315609.png
sdialog/evaluation/dialog2flow/util/visualization/imgs/square_14034302.png
sdialog/evaluation/dialog2flow/util/visualization/imgs/undo.png
sdialog/evaluation/dialog2flow/util/visualization/imgs/upload_5735876.png
sdialog/evaluation/dialog2flow/util/visualization/imgs/view_1_1.png
sdialog/evaluation/dialog2flow/util/visualization/imgs/view_1_132.png
sdialog/evaluation/dialog2flow/util/visualization/imgs/zoom_in.png
sdialog/evaluation/dialog2flow/util/visualization/imgs/zoom_in32.png
sdialog/evaluation/dialog2flow/util/visualization/imgs/zoom_out.png
sdialog/evaluation/dialog2flow/util/visualization/imgs/zoom_out32.png
sdialog/evaluation/dialog2flow/util/visualization/imgs/overlays/check.png
sdialog-0.4.0.dist-info/licenses/LICENSE
sdialog-0.4.0.dist-info/METADATA
sdialog-0.4.0.dist-info/WHEEL
sdialog-0.4.0.dist-info/top_level.txt
sdialog-0.4.0.dist-info/RECORD
