Metadata-Version: 2.4
Name: sdialog
Version: 0.4.0
Summary: Synthetic Dialogue Generation and Analysis
Author-email: Sergio Burdisso <sergio.burdisso@gmail.com>
Maintainer-email: Sergio Burdisso <sergio.burdisso@gmail.com>, Severin Baroudi <sevbargal@outlook.fr>, Yanis Labrak <yanis.labrak@univ-avignon.fr>
License-Expression: MIT
Project-URL: Homepage, https://sdialog.readthedocs.io
Project-URL: Issues, https://github.com/idiap/sdialog/issues
Project-URL: Source, https://github.com/idiap/sdialog
Project-URL: Documentation, https://sdialog.readthedocs.io
Classifier: Intended Audience :: Developers
Classifier: Intended Audience :: Education
Classifier: Intended Audience :: Science/Research
Classifier: Topic :: Scientific/Engineering
Classifier: Topic :: Scientific/Engineering :: Artificial Intelligence
Classifier: Topic :: Software Development
Classifier: Topic :: Software Development :: Libraries
Classifier: Topic :: Software Development :: Libraries :: Python Modules
Classifier: Programming Language :: Python :: 3
Classifier: Operating System :: OS Independent
Requires-Python: >=3.9
License-File: LICENSE
Requires-Dist: codecov
Requires-Dist: flake8
Requires-Dist: graphviz
Requires-Dist: Jinja2
Requires-Dist: matplotlib
Requires-Dist: networkx
Requires-Dist: numpy
Requires-Dist: pandas
Requires-Dist: tabulate
Requires-Dist: pre-commit
Requires-Dist: print-color
Requires-Dist: PyYAML
Requires-Dist: tqdm
Requires-Dist: tenacity
Requires-Dist: syllables
Requires-Dist: fastapi
Requires-Dist: uvicorn
Requires-Dist: langchain-huggingface
Requires-Dist: langchain-openai
Requires-Dist: langchain-google-genai
Requires-Dist: langchain-anthropic
Requires-Dist: langchain-aws
Requires-Dist: langchain-ollama
Requires-Dist: langchain<0.4.0; python_version < "3.10"
Requires-Dist: langchain; python_version >= "3.10"
Requires-Dist: sentence-transformers
Requires-Dist: huggingface_hub
Requires-Dist: simpleneighbors
Requires-Dist: scikit-learn
Requires-Dist: scipy
Requires-Dist: pydantic
Requires-Dist: transformers<=4.56.2; python_version < "3.10"
Requires-Dist: transformers; python_version >= "3.10"
Requires-Dist: torch
Requires-Dist: pytest
Requires-Dist: pytest-cov
Requires-Dist: ollama
Requires-Dist: openai
Provides-Extra: audio
Requires-Dist: soundfile; extra == "audio"
Requires-Dist: librosa; extra == "audio"
Requires-Dist: sox; extra == "audio"
Requires-Dist: jams; extra == "audio"
Requires-Dist: pyloudnorm; extra == "audio"
Requires-Dist: pyroomacoustics; extra == "audio"
Requires-Dist: datasets<=3.6.0; extra == "audio"
Requires-Dist: huggingface_hub[cli]; extra == "audio"
Requires-Dist: dscaper; extra == "audio"
Dynamic: license-file
